pyfx/__about__.py
pyfx/__init__.py
pyfx/__main__.py
pyfx/component.py
pyfx/exceptions.py
pyfx/footswitch.py
pyfx/knob.py
pyfx/logger.py
pyfx/pedal.py
pyfx/assets/attributions.md
pyfx/assets/down-arrow.png
pyfx/assets/icons.qrc
pyfx/assets/icons_rc.py
pyfx/assets/loop_arrows.png
pyfx/assets/minus.png
pyfx/assets/pause_button.png
pyfx/assets/play_button.png
pyfx/assets/plus.png
pyfx/assets/pyfx_logo.png
pyfx/assets/stop_button.png
pyfx/assets/up-arrow.png
pyfx/assets/audio/acoustic_melody_0.wav
pyfx/assets/audio/acoustic_melody_1.wav
pyfx/assets/audio/acoustic_melody_2.wav
pyfx/assets/audio/clean_guitar_loop.wav
pyfx/assets/audio/inde_rocking.wav
pyfx/assets/pedals/startup.cfg
pyfx/assets/pedals/delay/default_delay_pedal.py
pyfx/assets/pedals/delay/autogen/delay_pedal.py
pyfx/assets/pedals/delay/autogen/delay_pedal_variant_base.py
pyfx/assets/pedals/saturate/default_saturate_pedal.py
pyfx/assets/pedals/saturate/smooth_saturate_pedal.py
pyfx/assets/pedals/saturate/autogen/saturate_pedal.py
pyfx/assets/pedals/saturate/autogen/saturate_pedal_variant_base.py
pyfx/assets/pedals/volume/default_volume_pedal.py
pyfx/assets/pedals/volume/autogen/volume_pedal.py
pyfx/assets/pedals/volume/autogen/volume_pedal_variant_base.py
pyfx/audio/audio_consumer.py
pyfx/audio/audio_controller.py
pyfx/audio/audio_data_converter.py
pyfx/audio/audio_device.py
pyfx/audio/audio_driver.py
pyfx/audio/audio_interface_info.py
pyfx/audio/audio_processor.py
pyfx/audio/audio_source.py
pyfx/pedal_builder/pedal_builder.py
pyfx/pedal_builder/pedal_builder_app.py
pyfx/pedal_builder/pedal_builder_app_stylesheet.qss
pyfx/tools/build_and_open_app.py
pyfx/tools/compile_ui_files.py
pyfx/ui/audio_preferences_widget.ui
pyfx/ui/audio_preferences_widget_ui.py
pyfx/ui/channel_configuration_widget.ui
pyfx/ui/channel_configuration_widget_ui.py
pyfx/ui/footswitch_component.ui
pyfx/ui/footswitch_component_ui.py
pyfx/ui/footswitch_config_dialog.ui
pyfx/ui/footswitch_config_dialog_ui.py
pyfx/ui/knob_component.ui
pyfx_dev-1.0.0a4.dist-info/METADATA
pyfx_dev-1.0.0a4.dist-info/WHEEL
pyfx_dev-1.0.0a4.dist-info/licenses/LICENSE.txt
pyfx_dev-1.0.0a4.dist-info/RECORD
